pgspot/__init__.py
pgspot/__main__.py
pgspot/cli.py
pgspot/codes.py
pgspot/formatters.py
pgspot/path.py
pgspot/plpgsql.py
pgspot/state.py
pgspot/visitors.py
pgspot/pg_catalog/__init__.py
pgspot/pg_catalog/format.py
pgspot-0.9.1.dist-info/licenses/LICENSE
pgspot-0.9.1.dist-info/METADATA
pgspot-0.9.1.dist-info/WHEEL
pgspot-0.9.1.dist-info/entry_points.txt
pgspot-0.9.1.dist-info/top_level.txt
pgspot-0.9.1.dist-info/RECORD
