Metadata-Version: 2.4
Name: pgspot
Version: 0.9.1
Summary: Spot vulnerabilities in postgres extension scripts
Home-page: https://github.com/timescale/pgspot
Author: Timescale, Inc.
License: The PostgreSQL License
Project-URL: Bug Tracker, https://github.com/timescale/pgspot/issues
Keywords: postgresql
Classifier: Development Status :: 4 - Beta
Classifier: Intended Audience :: Developers
Classifier: License :: OSI Approved :: PostgreSQL License
Classifier: Operating System :: OS Independent
Classifier: Programming Language :: Python
Classifier: Programming Language :: Python :: 3.10
Classifier: Topic :: Software Development :: Libraries :: Python Modules
Classifier: Topic :: Software Development :: Quality Assurance
Requires-Python: >=3.10
License-File: LICENSE
Requires-Dist: pglast==7.7
Dynamic: license-file
